Metadata-Version: 1.0
Name: pytstools
Version: 0.1
Summary: This should be a short description of our project
Home-page: https://github.com/pvijaybhanu
Author: Vijay Peddimsetti
Author-email: pvijaybhanu@gmail.com
License: UNKNOWN
Platform: UNKNOWN
